spu-0.9.4.dist-info/METADATA
spu-0.9.4.dist-info/WHEEL
spu-0.9.4.dist-info/entry_points.txt
spu-0.9.4.dist-info/licenses/LICENSE
spu/__init__.py
spu/api.py
spu/experimental/__init__.py
spu/experimental/drop_cached_var_impl.py
spu/experimental/epsilon_impl.py
spu/experimental/make_cached_var_impl.py
spu/experimental/reveal_impl.py
spu/intrinsic/__init__.py
spu/intrinsic/add_new_intrinsic.py
spu/intrinsic/example_binary_impl.py
spu/intrinsic/example_impl.py
spu/libpsi.pyi
spu/libpsi.so
spu/libspu.pyi
spu/libspu.so
spu/ops/__init__.py
spu/ops/groupby/__init__.py
spu/ops/groupby/aggregation.py
spu/ops/groupby/groupby_test.py
spu/ops/groupby/groupby_via_shuffle.py
spu/ops/groupby/postprocess.py
spu/ops/groupby/segmentation.py
spu/ops/groupby/shuffle.py
spu/ops/groupby/utils.py
spu/psi.py
spu/utils/__init__.py
spu/utils/frontend.py
spu/utils/polyfill.py
spu/utils/simulation.py
spu/version.py
spu-0.9.4.dist-info/RECORD
