Metadata-Version: 2.4
Name: spu
Version: 0.9.4
Summary: spu
Author-Email: SecretFlow Team <secretflow-contact@service.alipay.com>
License-Expression: Apache-2.0
Classifier: Programming Language :: Python :: 3
Classifier: Programming Language :: Python :: 3.10
Classifier: Programming Language :: Python :: 3.11
Project-URL: Homepage, https://github.com/secretflow/spu
Project-URL: Repository, https://github.com/secretflow/spu
Requires-Python: <3.12,>=3.10
Requires-Dist: numpy<2,>=1.22.0
Requires-Dist: cloudpickle>=2.0.0
Requires-Dist: multiprocess>=0.70.12.2
Requires-Dist: cachetools>=5.0.0
Requires-Dist: jax[cpu]==0.6.2
Requires-Dist: termcolor>=2.0.0
